<?xml version="1.0" encoding="UTF-8"?> 
 <Lemmas>
<res>
<word>نشيد</word> 
 <lemma>نَشِيد</lemma>
</res>
<res>
<word>الفلاح</word> 
 <lemma>فَلَاح</lemma>
</res>

<res>
<word>القبلة</word> 
 <lemma>قِبْلَة</lemma>
</res>
<res>
<word>الأولى</word> 
 <lemma>أَوَّل</lemma>
</res>
<res>
<word>في</word> 
 <lemma>فِي</lemma>
</res>
<res>
<word>الصباح</word> 
 <lemma>صُبَاح</lemma>
</res>

<res>
<word>لجبهة</word> 
 <lemma>جَبْهَة</lemma>
</res>
<res>
<word>الفلاح</word> 
 <lemma>فَلَاح</lemma>
</res>

<res>
<word>لمعول</word> 
 <lemma>مَعُول</lemma>
</res>
<res>
<word>الفلاح</word> 
 <lemma>فَلَاح</lemma>
</res>

<res>
<word>لساعد</word> 
 <lemma>سَاعَدَ</lemma>
</res>
<res>
<word>الفلاح</word> 
 <lemma>فَلَاح</lemma>
</res>

<res>
<word>الساعد</word> 
 <lemma>سَاعِد</lemma>
</res>
<res>
<word>المفتول</word> 
 <lemma>مَفْتُول</lemma>
</res>
<res>
<word>تحبه</word> 
 <lemma>أَحَبَّ</lemma>
</res>
<res>
<word>الحقول</word> 
 <lemma>حَقْل</lemma>
</res>

<res>
<word>تعطيه</word> 
 <lemma>أَعْطَى</lemma>
</res>
<res>
<word>ما</word> 
 <lemma>مَا</lemma>
</res>
<res>
<word>يشاء</word> 
 <lemma>شَاءَ</lemma>
</res>
<res>
<word>من</word> 
 <lemma>مِنْ</lemma>
</res>
<res>
<word>ثمر</word> 
 <lemma>ثَمَرَة</lemma>
</res>

<res>
<word>من</word> 
 <lemma>مَنْ</lemma>
</res>
<res>
<word>غلة</word> 
 <lemma>غَلَّة</lemma>
</res>
<res>
<word>كدفقة</word> 
 <lemma>دِفْقَة</lemma>
</res>
<res>
<word>المطر</word> 
 <lemma>مَطَر</lemma>
</res>

<res>
<word>وتضحك</word> 
 <lemma>ضَحِكَ</lemma>
</res>
<res>
<word>البلاد</word> 
 <lemma>بِلَاد</lemma>
</res>
<res>
<word>لموسم</word> 
 <lemma>مَوْسِم</lemma>
</res>
<res>
<word>الحصاد</word> 
 <lemma>حِصَاد</lemma>
</res>

<res>
<word>ويسعد</word> 
 <lemma>أَسْعَدَ</lemma>
</res>
<res>
<word>البشر</word> 
 <lemma>بَشَر</lemma>
</res>

</Lemmas>
