<?xml version="1.0" encoding="UTF-8"?> 
 <Lemmas>
<res>
<word>أعمل</word> 
 <lemma>عَمِلَ</lemma>
</res>
<res>
<word>، </word> 
 <lemma>، </lemma>
</res>
<res>
<word>أسمع</word> 
 <lemma>سَمِعَ</lemma>
</res>
<res>
<word>ألحانا</word> 
 <lemma>لَحَّان</lemma>
</res>
<res>
<word>أعمل</word> 
 <lemma>عَمِلَ</lemma>
</res>
<res>
<word>أذكر</word> 
 <lemma>ذَكَرَ</lemma>
</res>
<res>
<word>خلانا</word> 
 <lemma>خَلَا</lemma>
</res>
<res>
<word>.</word> 
 <lemma>.</lemma>
</res>

<res>
<word>نتعاون</word> 
 <lemma>تَعَاوَنَ</lemma>
</res>
<res>
<word>، </word> 
 <lemma>، </lemma>
</res>
<res>
<word>نبذر</word> 
 <lemma>نَبْذَرَ</lemma>
</res>
<res>
<word>خضرا</word> 
 <lemma>أَخْضَر</lemma>
</res>
<res>
<word>نتعاون</word> 
 <lemma>تَعَاوَنَ</lemma>
</res>
<res>
<word>، </word> 
 <lemma>، </lemma>
</res>
<res>
<word>نغرس</word> 
 <lemma>غَرَسَ</lemma>
</res>
<res>
<word>شجرا</word> 
 <lemma>شَجَرَة</lemma>
</res>
<res>
<word>.</word> 
 <lemma>.</lemma>
</res>

<res>
<word>وصحابي</word> 
 <lemma>صَاحِب</lemma>
</res>
<res>
<word>، </word> 
 <lemma>، </lemma>
</res>
<res>
<word>عود</word> 
 <lemma>عُود</lemma>
</res>
<res>
<word>ووتر</word> 
 <lemma>وَتَر</lemma>
</res>
<res>
<word>نشدو</word> 
 <lemma>شَدَا</lemma>
</res>
<res>
<word>، </word> 
 <lemma>، </lemma>
</res>
<res>
<word>يا</word> 
 <lemma>يَا</lemma>
</res>
<res>
<word>هلا</word> 
 <lemma>هَلَّا</lemma>
</res>
<res>
<word>، </word> 
 <lemma>، </lemma>
</res>
<res>
<word>يا</word> 
 <lemma>يَا</lemma>
</res>
<res>
<word>مطر</word> 
 <lemma>مَطَر</lemma>
</res>
<res>
<word>!</word> 
 <lemma>!</lemma>
</res>

</Lemmas>
