<?xml version="1.0" encoding="UTF-8"?> 
 <Lemmas>
<res>
<word>قد</word> 
 <lemma>قَدْ</lemma>
</res>
<res>
<word>اختيرت</word> 
 <lemma>اخْتَارَ</lemma>
</res>
<res>
<word>لسفر</word> 
 <lemma>سَفَر</lemma>
</res>
<res>
<word>البعثة</word> 
 <lemma>بَعْثَة</lemma>
</res>
<res>
<word>سفينة</word> 
 <lemma>سَفِينَة</lemma>
</res>
<res>
<word> "</word> 
 <lemma> "</lemma>
</res>
<res>
<word>أصبهان</word> 
 <lemma>أصبهان</lemma>
</res>
<res>
<word>" </word> 
 <lemma>" </lemma>
</res>
<res>
<word>الفرنسية</word> 
 <lemma>فَرَنْسِيّ</lemma>
</res>
<res>
<word>الفقيرة</word> 
 <lemma>فَقِير</lemma>
</res>
<res>
<word>الرخيصة</word> 
 <lemma>رَخِيص</lemma>
</res>
<res>
<word>، </word> 
 <lemma>، </lemma>
</res>
<res>
<word>و</word> 
 <lemma>وَ</lemma>
</res>
<res>
<word>كان</word> 
 <lemma>كَانَ</lemma>
</res>
<res>
<word>اختيارها</word> 
 <lemma>اخْتِيَار</lemma>
</res>
<res>
<word>لونا</word> 
 <lemma>لَوْن</lemma>
</res>
<res>
<word>من</word> 
 <lemma>مِنْ</lemma>
</res>
<res>
<word>الاقتصاد</word> 
 <lemma>اقْتِصَاد</lemma>
</res>
<res>
<word>، </word> 
 <lemma>، </lemma>
</res>
<res>
<word>و</word> 
 <lemma>وَ</lemma>
</res>
<res>
<word>كانت</word> 
 <lemma>كَانَ</lemma>
</res>
<res>
<word>على</word> 
 <lemma>عَلَى</lemma>
</res>
<res>
<word>بؤسها</word> 
 <lemma>بُؤْس</lemma>
</res>
<res>
<word>مرحة</word> 
 <lemma>مَرِح</lemma>
</res>
<res>
<word>تحب</word> 
 <lemma>أَحَبَّ</lemma>
</res>
<res>
<word>الرقص</word> 
 <lemma>رَقْص</lemma>
</res>
<res>
<word>في</word> 
 <lemma>فِي</lemma>
</res>
<res>
<word>البحر</word> 
 <lemma>بَحَر</lemma>
</res>
<res>
<word>، </word> 
 <lemma>، </lemma>
</res>
<res>
<word>وتؤثر</word> 
 <lemma>أَثَّرَ</lemma>
</res>
<res>
<word>المهل</word> 
 <lemma>مَهَل</lemma>
</res>
<res>
<word>على</word> 
 <lemma>عَلَى</lemma>
</res>
<res>
<word>العجل</word> 
 <lemma>عَجَل</lemma>
</res>
<res>
<word>، </word> 
 <lemma>، </lemma>
</res>
<res>
<word>و</word> 
 <lemma>وَ</lemma>
</res>
<res>
<word>تفضل</word> 
 <lemma>أَفْضَلَ</lemma>
</res>
<res>
<word>الأناة</word> 
 <lemma>أَنَاة</lemma>
</res>
<res>
<word>على</word> 
 <lemma>عَلَى</lemma>
</res>
<res>
<word>السرعة</word> 
 <lemma>سُرْعَة</lemma>
</res>
<res>
<word>.</word> 
 <lemma>.</lemma>
</res>

<res>
<word>و</word> 
 <lemma>وَ</lemma>
</res>
<res>
<word>كانت</word> 
 <lemma>كَانَ</lemma>
</res>
<res>
<word>السفن</word> 
 <lemma>سَفِينَة</lemma>
</res>
<res>
<word>تعبر</word> 
 <lemma>عَبَّرَ</lemma>
</res>
<res>
<word>البحر</word> 
 <lemma>بَحْر</lemma>
</res>
<res>
<word>في</word> 
 <lemma>فِي</lemma>
</res>
<res>
<word>ستة</word> 
 <lemma>سِتّ</lemma>
</res>
<res>
<word>أيام</word> 
 <lemma>يَوْم</lemma>
</res>
<res>
<word>، </word> 
 <lemma>، </lemma>
</res>
<res>
<word>فأما</word> 
 <lemma>أَمَّا</lemma>
</res>
<res>
<word>السفينة</word> 
 <lemma>سَفِينَة</lemma>
</res>
<res>
<word>أصبهان</word> 
 <lemma>أصبهان</lemma>
</res>
<res>
<word>، </word> 
 <lemma>، </lemma>
</res>
<res>
<word>فكانت</word> 
 <lemma>كَانَ</lemma>
</res>
<res>
<word>تحب</word> 
 <lemma>أَحَبَّ</lemma>
</res>
<res>
<word>البحر</word> 
 <lemma>بَحْر</lemma>
</res>
<res>
<word>و</word> 
 <lemma>وَ</lemma>
</res>
<res>
<word>تؤثر</word> 
 <lemma>أَثَّرَ</lemma>
</res>
<res>
<word>أن</word> 
 <lemma>أَنْ</lemma>
</res>
<res>
<word>تعبره</word> 
 <lemma>عَبَّرَ</lemma>
</res>
<res>
<word>في</word> 
 <lemma>فِي</lemma>
</res>
<res>
<word>أحد</word> 
 <lemma>أَحَد</lemma>
</res>
<res>
<word>عشر</word> 
 <lemma>عُشْر</lemma>
</res>
<res>
<word>يوما</word> 
 <lemma>يَوْم</lemma>
</res>
<res>
<word>.</word> 
 <lemma>.</lemma>
</res>

<res>
<word>و</word> 
 <lemma>وَ</lemma>
</res>
<res>
<word>صعد</word> 
 <lemma>صَعِدَ</lemma>
</res>
<res>
<word>الفتى</word> 
 <lemma>فَتَى</lemma>
</res>
<res>
<word>إلى</word> 
 <lemma>إِلَى</lemma>
</res>
<res>
<word>أصبهان</word> 
 <lemma>أصبهان</lemma>
</res>
<res>
<word>يتعثر</word> 
 <lemma>تَعَثَّرَ</lemma>
</res>
<res>
<word>في</word> 
 <lemma>فِي</lemma>
</res>
<res>
<word>جبته</word> 
 <lemma>جَابَ</lemma>
</res>
<res>
<word>و</word> 
 <lemma>وَ</lemma>
</res>
<res>
<word>قفطانه</word> 
 <lemma>قَفْط</lemma>
</res>
<res>
<word>فرحا</word> 
 <lemma>فَرَح</lemma>
</res>
<res>
<word>، </word> 
 <lemma>، </lemma>
</res>
<res>
<word>و</word> 
 <lemma>وَ</lemma>
</res>
<res>
<word>لم</word> 
 <lemma>لَمْ</lemma>
</res>
<res>
<word>يكد</word> 
 <lemma>كَادَ</lemma>
</res>
<res>
<word>أن</word> 
 <lemma>أَنْ</lemma>
</res>
<res>
<word>يبلغ</word> 
 <lemma>بَلَغَ</lemma>
</res>
<res>
<word>غرفته</word> 
 <lemma>غُرْفَة</lemma>
</res>
<res>
<word>في</word> 
 <lemma>فِي</lemma>
</res>
<res>
<word>الدرجة</word> 
 <lemma>دَرَجَة</lemma>
</res>
<res>
<word>الثانية</word> 
 <lemma>ثَانِي</lemma>
</res>
<res>
<word>حتي</word> 
 <lemma>حَتّ</lemma>
</res>
<res>
<word>خرج</word> 
 <lemma>خَرَجَ</lemma>
</res>
<res>
<word>من</word> 
 <lemma>مِنْ</lemma>
</res>
<res>
<word>جبته</word> 
 <lemma>جَابَ</lemma>
</res>
<res>
<word>و</word> 
 <lemma>وَ</lemma>
</res>
<res>
<word>قفطانه</word> 
 <lemma>قَفْط</lemma>
</res>
<res>
<word>و</word> 
 <lemma>وَ</lemma>
</res>
<res>
<word>تخفف</word> 
 <lemma>خَفَّفَ</lemma>
</res>
<res>
<word>من</word> 
 <lemma>مِنْ</lemma>
</res>
<res>
<word>عمامته</word> 
 <lemma>عَمَّام</lemma>
</res>
<res>
<word>، </word> 
 <lemma>، </lemma>
</res>
<res>
<word>و</word> 
 <lemma>وَ</lemma>
</res>
<res>
<word>دخل</word> 
 <lemma>دَخَلَ</lemma>
</res>
<res>
<word>في</word> 
 <lemma>فِي</lemma>
</res>
<res>
<word>ذلك</word> 
 <lemma>ذَا</lemma>
</res>
<res>
<word>الزي</word> 
 <lemma>زِيّ</lemma>
</res>
<res>
<word>الأوربي</word> 
 <lemma>الأوربي</lemma>
</res>
<res>
<word>.</word> 
 <lemma>.</lemma>
</res>

</Lemmas>
